CHANGES.rst
DESCRIPTION.rst
MANIFEST.in
README.rst
setup.cfg
setup.py
brabbel/__init__.py
brabbel/expression.py
brabbel/functions.py
brabbel/operators.py
brabbel/parser.py
brabbel.egg-info/PKG-INFO
brabbel.egg-info/SOURCES.txt
brabbel.egg-info/dependency_links.txt
brabbel.egg-info/requires.txt
brabbel.egg-info/top_level.txt