Metadata-Version: 1.1
Name: brabbel
Version: 0.4.2
Summary: A simple python based expression language
Home-page: https://bitbucket.org/ti/brabbel
Author: Torsten Irlaender
Author-email: torsten.irlaender@googlemail.com
License: GNU General Public License v2 or later (GPLv2+)
Platform: UNKNOWN
Classifier: Development Status :: 4 - Beta
Classifier: Intended Audience :: Developers
Classifier: License :: OSI Approved :: GNU General Public License v2 or later (GPLv2+)
Classifier: Programming Language :: Python :: 2.7
Classifier: Programming Language :: Python :: 3
Classifier: Programming Language :: Python :: 3.3
Classifier: Programming Language :: Python :: 3.4
